robot/__init__.py
robot/robot.py
robot_scratch4robots-1.0.7.dist-info/METADATA
robot_scratch4robots-1.0.7.dist-info/RECORD
robot_scratch4robots-1.0.7.dist-info/WHEEL
robot_scratch4robots-1.0.7.dist-info/top_level.txt
